{"stats":{"minecraft:crafted":{"skyblock:vigilant_slab":6,"skyblock:abyss_jungle_slab":6,"skyblock:end_stairs":4,"skyblock:sal_shroom_slab":6,"skyblock:abysculk_stairs":4,"skyblock:bluishe_slab":6,"skyblock:blaru_slab":6,"minecraft:lectern":1,"skyblock:callery_stairs":4,"skyblock:slimed_slab":6,"skyblock:abysculk_slab":6,"skyblock:blaru_stairs":4,"skyblock:end_slab":6,"skyblock:frozen_stairs":4,"skyblock:bog_shroom_slab":6,"skyblock:sal_shroom_stairs":4,"skyblock:callery_slab":6,"skyblock:frozen_slab":6,"skyblock:end_emerald":9,"skyblock:bog_shroom_stairs":4,"skyblock:end_emerald_block":1,"skyblock:vigilant_stairs":4,"skyblock:azalea_slab":6,"skyblock:azalea_stairs":4,"skyblock:slimed_stairs":4,"skyblock:bluishe_stairs":4,"skyblock:abyss_jungle_stairs":4},"minecraft:used":{"skyblock:azalea_slab":1,"skyblock:twin_bow":8},"minecraft:custom":{"minecraft:time_since_rest":6231,"minecraft:crouch_one_cm":15,"minecraft:sprint_one_cm":5271,"minecraft:play_time":6231,"minecraft:walk_one_cm":2171,"minecraft:sneak_time":16,"minecraft:jump":69,"minecraft:leave_game":3,"minecraft:time_since_death":6231,"minecraft:total_world_time":9481,"minecraft:interact_with_crafting_table":4,"minecraft:fly_one_cm":31629}},"DataVersion":3465}