{"stats":{"minecraft:custom":{"minecraft:time_since_rest":4857,"minecraft:crouch_one_cm":279,"minecraft:play_time":4857,"minecraft:sprint_one_cm":6471,"minecraft:walk_one_cm":3363,"minecraft:sneak_time":158,"minecraft:jump":92,"minecraft:leave_game":1,"minecraft:time_since_death":4857,"minecraft:total_world_time":14211,"minecraft:fly_one_cm":36690},"minecraft:used":{"skyblock:bog_shroom_leaves":12,"skyblock:bluishe_planks":4,"skyblock:blue_wart":9,"skyblock:stripped_bog_shroom_log":2,"skyblock:stripped_bluishe_hyphae":2,"skyblock:flowering_callery_leaves":13,"skyblock:stripped_bog_shroom_wood":2,"minecraft:flint_and_steel":9,"minecraft:grass_block":5,"skyblock:stripped_bluishe_stem":2,"skyblock:bluishe_stem":2,"skyblock:bog_shroom_wood":2,"skyblock:bluishe_hyphae":2,"skyblock:bog_shroom_log":2,"skyblock:azalea_log":8,"skyblock:bog_shroom_planks":4}},"DataVersion":3337}