{"stats":{"minecraft:used":{"minecraft:redstone_torch":31,"minecraft:sticky_piston":11,"minecraft:oak_trapdoor":1,"minecraft:stone_brick_slab":6,"minecraft:flower_pot":28,"minecraft:dead_tube_coral_block":70,"betterend:andesite_pedestal":3,"minecraft:flint_and_steel":30,"minecraft:armor_stand":2,"minecraft:redstone":8,"minecraft:polished_andesite":229,"minecraft:string":2,"minecraft:polished_andesite_stairs":41,"minecraft:stone_button":74,"skyblock:andesite_pillar":80,"minecraft:stone":2,"minecraft:polished_granite":14,"minecraft:gravel":66,"minecraft:polished_andesite_slab":14,"skyblock:diorite_pillar":2,"minecraft:stone_brick_stairs":39,"minecraft:stone_bricks":208,"minecraft:cracked_stone_bricks":69,"minecraft:bedrock":1,"minecraft:chiseled_stone_bricks":301,"minecraft:reinforced_deepslate":1,"minecraft:cobblestone":310,"minecraft:cobblestone_wall":36,"minecraft:andesite":87,"minecraft:black_candle":12,"minecraft:campfire":1,"minecraft:skeleton_skull":5,"minecraft:stone_brick_wall":2,"minecraft:polished_granite_slab":30,"minecraft:candle":59,"minecraft:cobweb":48},"minecraft:picked_up":{"minecraft:redstone_torch":1},"minecraft:custom":{"minecraft:time_since_rest":88447,"minecraft:sprint_one_cm":130791,"minecraft:walk_one_cm":171428,"minecraft:fly_one_cm":302560,"minecraft:crouch_one_cm":6092,"minecraft:play_time":88447,"minecraft:sneak_time":2187,"minecraft:pot_flower":29,"minecraft:jump":480,"minecraft:leave_game":1,"minecraft:time_since_death":88447,"minecraft:total_world_time":128854}},"DataVersion":3337}