{"stats":{"minecraft:custom":{"minecraft:jump":63,"minecraft:time_since_rest":1191,"minecraft:leave_game":1,"minecraft:crouch_one_cm":56,"minecraft:sprint_one_cm":3579,"minecraft:play_time":1191,"minecraft:damage_taken":32,"minecraft:time_since_death":1191,"minecraft:walk_one_cm":1240,"minecraft:sneak_time":7,"minecraft:total_world_time":2242,"minecraft:damage_resisted":8,"minecraft:fall_one_cm":1479,"minecraft:fly_one_cm":15139},"minecraft:mined":{"skyblock:abyss_slime_block":19},"minecraft:picked_up":{"skyblock:abyss_slime_block":19},"minecraft:used":{"skyblock:abyss_slime_block":19}},"DataVersion":3465}