{
  "betterend:recipes/misc/eternal_crystal": {
    "criteria": {
      "has_item.minecraft.end_crystal": "2023-05-12 08:40:17 +0200"
    },
    "done": true
  },
  "minecraft:recipes/misc/coal": {
    "criteria": {
      "has_coal_block": "2023-05-12 08:40:17 +0200"
    },
    "done": true
  },
  "minecraft:recipes/decorations/crafting_table": {
    "criteria": {
      "unlock_right_away": "2023-05-12 08:40:17 +0200"
    },
    "done": true
  },
  "minecraft:recipes/decorations/chest": {
    "criteria": {
      "has_lots_of_items": "2023-05-12 08:40:17 +0200"
    },
    "done": true
  },
  "betterend:recipes/misc/ender_perl_to_block": {
    "criteria": {
      "has_ender_pearl": "2023-05-12 08:42:18 +0200"
    },
    "done": true
  },
  "minecraft:adventure/honey_block_slide": {
    "criteria": {
      "honey_block_slide": "2023-05-12 08:40:46 +0200"
    },
    "done": true
  },
  "minecraft:nether/netherite_armor": {
    "criteria": {
      "netherite_armor": "2023-05-12 08:40:17 +0200"
    },
    "done": true
  },
  "betterend:root": {
    "criteria": {
      "welcome": "2023-05-12 08:40:19 +0200"
    },
    "done": true
  },
  "betterend:recipes/misc/ender_eye_amber": {
    "criteria": {
      "has_ender_pearl": "2023-05-12 08:42:18 +0200"
    },
    "done": true
  },
  "betterend:recipes/misc/ender_pearl_to_dust": {
    "criteria": {
      "has_item.minecraft.ender_pearl": "2023-05-12 08:42:18 +0200"
    },
    "done": true
  },
  "minecraft:adventure/adventuring_time": {
    "criteria": {
      "minecraft:plains": "2023-05-12 08:40:19 +0200"
    },
    "done": false
  },
  "betterend:recipes/misc/infusion_pedestal": {
    "criteria": {
      "has_ender_pearl": "2023-05-12 08:42:18 +0200"
    },
    "done": true
  },
  "DataVersion": 3337
}